CHANGES.rst
LICENSE
MANIFEST.in
README.rst
setup.cfg
setup.py
tox.ini
morepath_rest_dump_load/__init__.py
morepath_rest_dump_load/app.py
morepath_rest_dump_load/model.py
morepath_rest_dump_load/path.py
morepath_rest_dump_load/run.py
morepath_rest_dump_load/view.py
morepath_rest_dump_load.egg-info/PKG-INFO
morepath_rest_dump_load.egg-info/SOURCES.txt
morepath_rest_dump_load.egg-info/dependency_links.txt
morepath_rest_dump_load.egg-info/entry_points.txt
morepath_rest_dump_load.egg-info/not-zip-safe
morepath_rest_dump_load.egg-info/requires.txt
morepath_rest_dump_load.egg-info/top_level.txt
morepath_rest_dump_load/tests/__init__.py
morepath_rest_dump_load/tests/test_rest.py