Metadata-Version: 1.1
Name: morepath-rest-dump-load
Version: 0.1
Summary: Morepath REST Demo
Home-page: https://github.com/morepath/morepath_rest_dump_load
Author: Morepath developers
Author-email: morepath@googlegroups.com
License: BSD
Platform: UNKNOWN
Classifier: Intended Audience :: Developers
Classifier: Environment :: Web Environment
Classifier: License :: OSI Approved :: BSD License
Classifier: Topic :: Internet :: WWW/HTTP :: WSGI
Classifier: Programming Language :: Python :: 2.7
Classifier: Programming Language :: Python :: 3.4
Classifier: Programming Language :: Python :: 3.5
